isocor/__init__.py
isocor/__main__.py
isocor/base.py
isocor/mscorrectors.py
isocor/data/Data_example.tsv
isocor/data/Derivatives.dat
isocor/data/Isotopes.dat
isocor/data/Metabolites.dat
isocor/tests/__init__.py
isocor/tests/conftest.py
isocor/tests/test_all_cases.py
isocor/tests/test_correction_matrix_HighRes_resolved.py
isocor/tests/test_correction_matrix_HighRes_unresolved.py
isocor/tests/test_correction_matrix_LowRes.py
isocor/tests/test_correction_process_HighRes.py
isocor/tests/test_correction_process_LowRes.py
isocor/tests/test_factory.py
isocor/tests/test_isotopic_cluster_HighRes.py
isocor/tests/test_isotopic_cluster_LowRes.py
isocor/tests/test_m_min_constant.py
isocor/tests/test_m_min_orbitrap.py
isocor/ui/__init__.py
isocor/ui/isocorcli.py
isocor/ui/isocordb.py
isocor/ui/isocorgui.py
isocor-2.2.3.dist-info/licenses/LICENSE.md
isocor-2.2.3.dist-info/METADATA
isocor-2.2.3.dist-info/WHEEL
isocor-2.2.3.dist-info/entry_points.txt
isocor-2.2.3.dist-info/top_level.txt
isocor-2.2.3.dist-info/RECORD
