Metadata-Version: 2.4
Name: IsoCor
Version: 2.2.3
Summary: IsoCor: Isotope Correction for mass spectrometry labeling experiments
Home-page: https://github.com/MetaSys-LISBP/IsoCor/
Author: Pierre Millard, Baudoin Délépine, Matthieu Guionnet
Author-email: millard@insa-toulouse.fr
Classifier: Programming Language :: Python :: 3.7
Classifier: Programming Language :: Python :: 3.8
Classifier: Programming Language :: Python :: 3.9
Classifier: Programming Language :: Python :: 3.10
Classifier: Programming Language :: Python :: 3.11
Classifier: Programming Language :: Python :: 3.12
Classifier: License :: OSI Approved :: GNU General Public License v3 or later (GPLv3+)
Classifier: Operating System :: OS Independent
Classifier: Intended Audience :: Science/Research
Classifier: Topic :: Scientific/Engineering :: Bio-Informatics
Requires-Python: >=3.7
License-File: LICENSE.md
Requires-Dist: pandas>=0.17.1
Requires-Dist: scipy>=0.12.1
Provides-Extra: testing
Requires-Dist: pytest>=7.1.2; extra == "testing"
Requires-Dist: tox>=3.25.0; extra == "testing"
Dynamic: license-file
